pyart/LICENSE.txt
pyart/__init__.py
pyart/_debug_info.py
pyart/config.py
pyart/default_config.py
pyart/exceptions.py
pyart/lazydict.py
pyart/__check_build/README
pyart/__check_build/__init__.py
pyart/__check_build/_check_build.c
pyart/__check_build/_check_build.cpython-314t-x86_64-linux-gnu.so
pyart/__check_build/_check_build.pyx
pyart/aux_io/__init__.py
pyart/aux_io/_lzw.cpython-314t-x86_64-linux-gnu.so
pyart/aux_io/arm_vpt.py
pyart/aux_io/cf1.py
pyart/aux_io/cf1_cartesian.py
pyart/aux_io/d3r_gcpex_nc.py
pyart/aux_io/dn_to_float.py
pyart/aux_io/edge_netcdf.py
pyart/aux_io/gamic_hdf5.py
pyart/aux_io/gamicfile.py
pyart/aux_io/hpl_reader.py
pyart/aux_io/knmi_h5.py
pyart/aux_io/lzw15.py
pyart/aux_io/mch_dat_reader.py
pyart/aux_io/metranet_c.py
pyart/aux_io/metranet_cartesian_reader.py
pyart/aux_io/metranet_python.py
pyart/aux_io/metranet_reader.py
pyart/aux_io/mf_bin_reader.py
pyart/aux_io/mf_dat_reader.py
pyart/aux_io/mf_grib_reader.py
pyart/aux_io/mf_png_reader.py
pyart/aux_io/noxp_iphex_nc.py
pyart/aux_io/odim_h5.py
pyart/aux_io/odim_h5_writer.py
pyart/aux_io/pattern.py
pyart/aux_io/pmfile_structure.py
pyart/aux_io/rad4alp_bin_reader.py
pyart/aux_io/rad4alp_gif_reader.py
pyart/aux_io/rad4alp_iq_reader.py
pyart/aux_io/radx.py
pyart/aux_io/rainbow_psr.py
pyart/aux_io/rainbow_wrl.py
pyart/aux_io/sinarame_h5.py
pyart/aux_io/skyecho.py
pyart/aux_io/spectra.py
pyart/aux_io/swissbirdradar.py
pyart/aux_io/lzw/_lzw.c
pyart/aux_io/lzw/_lzw.pyx
pyart/aux_io/lzw/bitx.c
pyart/aux_io/lzw/bitx.h
pyart/aux_io/lzw/lzw.c
pyart/aux_io/lzw/lzw.h
pyart/bridge/__init__.py
pyart/bridge/wradlib_bridge.py
pyart/core/__init__.py
pyart/core/grid.py
pyart/core/radar.py
pyart/core/radar_spectra.py
pyart/core/transforms.py
pyart/core/wind_profile.py
pyart/correct/__init__.py
pyart/correct/_common_dealias.py
pyart/correct/_fast_edge_finder.c
pyart/correct/_fast_edge_finder.cpython-314t-x86_64-linux-gnu.so
pyart_mch-2.3.1.dist-info/METADATA
pyart_mch-2.3.1.dist-info/WHEEL
pyart_mch-2.3.1.dist-info/top_level.txt
pyart_mch-2.3.1.dist-info/RECORD
pyart_mch-2.3.1.dist-info/licenses/LICENSE.txt
