Metadata-Version: 2.4
Name: pyart_mch
Version: 2.3.1
Summary: MCH Py-ART: Python ARM Radar Toolkit - MeteoSwiss version
Home-page: https://github.com/MeteoSwiss/pyart
Author: MeteoSwiss Py-ART Developers
Author-email: daniel.wolfensberger@meteoswiss.ch
Maintainer: MeteoSwiss Py-ART Developers
Maintainer-email: daniel.wolfensberger@meteoswiss.ch
License: BSD
Platform: Linux
Platform: Mac OS-X
Platform: Unix
Classifier:     Development Status :: 5 - Production/Stable
Classifier:     Intended Audience :: Science/Research
Classifier:     Intended Audience :: Developers
Classifier:     License :: OSI Approved :: BSD License
Classifier:     Programming Language :: Python
Classifier:     Programming Language :: Python :: 3
Classifier:     Programming Language :: Python :: 3.6
Classifier:     Programming Language :: Python :: 3.7
Classifier:     Programming Language :: Python :: 3.8
Classifier:     Programming Language :: Python :: 3.9
Classifier:     Programming Language :: Python :: 3.10
Classifier:     Programming Language :: C
Classifier:     Programming Language :: Cython
Classifier:     Topic :: Scientific/Engineering
Classifier:     Topic :: Scientific/Engineering :: Atmospheric Science
Classifier:     Operating System :: POSIX :: Linux
Classifier:     Operating System :: MacOS :: MacOS X
Classifier:     Operating System :: Microsoft :: Windows
Classifier:     Framework :: Matplotlib
License-File: LICENSE.txt
Requires-Dist: numpy
Requires-Dist: scipy
Requires-Dist: netCDF4
Requires-Dist: matplotlib
Requires-Dist: pooch
Requires-Dist: cftime
Requires-Dist: fsspec
Requires-Dist: s3fs
Requires-Dist: open_radar_data
Requires-Dist: xradar
Requires-Dist: pandas
Requires-Dist: pygrib
Requires-Dist: mda-xdrlib
Requires-Dist: xarray
Requires-Dist: cmweather
Requires-Dist: cartopy
Dynamic: author
Dynamic: author-email
Dynamic: classifier
Dynamic: description
Dynamic: home-page
Dynamic: license
Dynamic: license-file
Dynamic: maintainer
Dynamic: maintainer-email
Dynamic: platform
Dynamic: requires-dist
Dynamic: summary
